<?xml version="1.0" encoding="UTF-8"?><FORM><SCREEN NAME="CVS_ASIGN" MAIN_WIN="Y" TITLE="Kiểm duyệt gán" POSITION="template" TMP_SCR_TYPE="L"><EXIT_BTN>2</EXIT_BTN><HEADER><TAB ID="TAB_HEADER"><LBL></LBL></TAB></HEADER><BODY><TAB ID="TAB_MAIN"><LBL></LBL><SECTION ID="SEC_1" COLLAPSE="N"><LBL></LBL><PART ID="P1" NAME="P1" WIDTH="100"><SPRTCNT>3</SPRTCNT><FLDSET ID="FST_1" VIEW="SE" TYPE="SE" INDEX="1"><LBL>Chi tiết hợp đồng</LBL><BLOCK>BLK_ASIGNMNT_VALIDATIONS</BLOCK><HREQ>0</HREQ><HEIGHT></HEIGHT><WIDTH></WIDTH><FIELD INDEX="" CONTROL="N" SPRT="1"><NAME>TXTPRD</NAME><TYPE>TEXT</TYPE><LBL>Mã sản phẩm</LBL><MAXLENGTH></MAXLENGTH><READ_ONLY>-1</READ_ONLY><DTYPE>VARCHAR2</DTYPE><SIZE></SIZE><ROWS></ROWS><COLS></COLS></FIELD><FIELD INDEX="" CONTROL="N" SPRT="2"><NAME>TXTPRDDESC</NAME><TYPE>TEXT</TYPE><LBL>Mô tả sản phẩm</LBL><MAXLENGTH></MAXLENGTH><READ_ONLY>-1</READ_ONLY><DTYPE>VARCHAR2</DTYPE><SIZE></SIZE><ROWS></ROWS><COLS></COLS></FIELD><FIELD INDEX="" CONTROL="N" SPRT="3"><NAME>TXTPRDTYPE</NAME><TYPE>TEXT</TYPE><LBL>Loại sản phẩm</LBL><MAXLENGTH></MAXLENGTH><READ_ONLY>-1</READ_ONLY><DTYPE>VARCHAR2</DTYPE><SIZE></SIZE><ROWS></ROWS><COLS></COLS></FIELD><FIELD INDEX="" CONTROL="N" SPRT="1"><NAME>CONTREFNO</NAME><TYPE>TEXT</TYPE><LBL>Số tham chiếu hợp đồng</LBL><MAXLENGTH>16</MAXLENGTH><READ_ONLY>-1</READ_ONLY><DTYPE>VARCHAR2</DTYPE><SIZE></SIZE><ROWS></ROWS><COLS></COLS></FIELD><FIELD INDEX="" CONTROL="N" SPRT="2"><NAME>TXTUSRREFNO</NAME><TYPE>TEXT</TYPE><LBL>Số tham chiếu người dùng</LBL><MAXLENGTH></MAXLENGTH><READ_ONLY>-1</READ_ONLY><DTYPE>VARCHAR2</DTYPE><SIZE></SIZE><ROWS></ROWS><COLS></COLS></FIELD><FIELD INDEX="" CONTROL="N" SPRT="3"><NAME>VERSIONNO</NAME><TYPE>TEXT</TYPE><MAX_DECIMALS>0</MAX_DECIMALS><LBL>Số thứ tự sự kiện</LBL><MAXLENGTH>4</MAXLENGTH><READ_ONLY>-1</READ_ONLY><DTYPE>NUMBER</DTYPE><MAX_VAL></MAX_VAL><MIN_VAL></MIN_VAL><SIZE></SIZE><ROWS></ROWS><COLS></COLS></FIELD><FIELD INDEX="" CONTROL="N" SPRT="1"><NAME>TXTCUST</NAME><TYPE>TEXT</TYPE><LBL>Khách hàng</LBL><MAXLENGTH></MAXLENGTH><READ_ONLY>-1</READ_ONLY><DTYPE>VARCHAR2</DTYPE><SIZE></SIZE><ROWS></ROWS><COLS></COLS></FIELD><FIELD INDEX="" CONTROL="N" SPRT="2"><NAME>TXTCUSTNAME</NAME><TYPE>TEXT</TYPE><LBL>Tên khách hàng</LBL><MAXLENGTH></MAXLENGTH><READ_ONLY>-1</READ_ONLY><DTYPE>VARCHAR2</DTYPE><SIZE></SIZE><ROWS></ROWS><COLS></COLS></FIELD><FIELD INDEX="" CONTROL="N" SPRT="3"><NAME>TXTFACILITY</NAME><TYPE>TEXT</TYPE><LBL>Tên hạn mức</LBL><MAXLENGTH></MAXLENGTH><READ_ONLY>-1</READ_ONLY><DTYPE>VARCHAR2</DTYPE><SIZE></SIZE><ROWS></ROWS><COLS></COLS></FIELD></FLDSET><FLDSET ID="FST_2" VIEW="SE" TYPE="SE" INDEX="2"><LBL>Kiểm duyệt gán</LBL><BLOCK>BLK_ASIGNMNT_VALIDATIONS</BLOCK><HREQ>0</HREQ><HEIGHT></HEIGHT><WIDTH></WIDTH><FIELD INDEX="" CONTROL="N" SPRT="1"><NAME>AGNTCONSNTREQ</NAME><TYPE>CHECKBOX</TYPE><CUSTOM><ON>Y</ON><OFF>N</OFF></CUSTOM><CHECKED>N</CHECKED><LBL>Yêu cầu có sự đồng ý của đại lý</LBL><MAXLENGTH>1</MAXLENGTH><DTYPE>VARCHAR2</DTYPE><SIZE></SIZE><ROWS></ROWS><COLS></COLS></FIELD><FIELD INDEX="" CONTROL="N" SPRT="2"><NAME>ACCEPTAFFILETRS</NAME><TYPE>CHECKBOX</TYPE><CUSTOM><ON>Y</ON><OFF>N</OFF></CUSTOM><CHECKED>N</CHECKED><LBL>Thư của chi nhánh được chấp nhận</LBL><MAXLENGTH>1</MAXLENGTH><DTYPE>VARCHAR2</DTYPE><SIZE></SIZE><ROWS></ROWS><COLS></COLS></FIELD></FLDSET></PART></SECTION><SECTION ID="SEC_2" COLLAPSE="N"><LBL></LBL><PART ID="P2" NAME="P2" WIDTH="100"></PART></SECTION><SECTION ID="SEC_3" COLLAPSE="N"><LBL></LBL><PART ID="P3_1" NAME="P3_1" WIDTH="50"><FLDSET ID="FST_3" VIEW="SE" TYPE="SE" INDEX="1"><LBL>Kiểm duyệt số tiền chuyển</LBL><BLOCK>BLK_ASIGNMNT_VALIDATIONS</BLOCK><HREQ>0</HREQ><HEIGHT></HEIGHT><WIDTH></WIDTH><FIELD INDEX="" CONTROL="N"><NAME>APLYTRFRAMTVALID</NAME><TYPE>CHECKBOX</TYPE><CUSTOM><ON>Y</ON><OFF>N</OFF></CUSTOM><CHECKED>N</CHECKED><LBL>Áp kiểm duyệt số tiền chuyển</LBL><MAXLENGTH>1</MAXLENGTH><DTYPE>VARCHAR2</DTYPE><SIZE></SIZE><ROWS></ROWS><COLS></COLS></FIELD><FIELD INDEX="" CONTROL="N"><NAME>TXTCONTCCY</NAME><TYPE>HIDDEN</TYPE><LBL>Loại tiền</LBL><MAXLENGTH></MAXLENGTH><HIDDEN>-1</HIDDEN><DTYPE>VARCHAR2</DTYPE><SIZE></SIZE><ROWS></ROWS><COLS></COLS></FIELD><FIELD INDEX="" CONTROL="N"><NAME>MINTRFRAMT</NAME><TYPE>AMOUNT</TYPE><MAX_DECIMALS></MAX_DECIMALS><LBL>Số tiền chuyển tối thiểu</LBL><MAXLENGTH></MAXLENGTH><DTYPE>NUMBER</DTYPE><MAX_VAL></MAX_VAL><MIN_VAL></MIN_VAL><SIZE></SIZE><ROWS></ROWS><COLS></COLS><RELATED_FIELD>TXTCONTCCY</RELATED_FIELD></FIELD><FIELD INDEX="" CONTROL="N"><NAME>MINAMTAFTERTRFR</NAME><TYPE>AMOUNT</TYPE><MAX_DECIMALS></MAX_DECIMALS><LBL>Số tiền tối thiểu sau khi chuyển</LBL><MAXLENGTH></MAXLENGTH><DTYPE>NUMBER</DTYPE><MAX_VAL></MAX_VAL><MIN_VAL></MIN_VAL><SIZE></SIZE><ROWS></ROWS><COLS></COLS><RELATED_FIELD>TXTCONTCCY</RELATED_FIELD></FIELD><FIELD INDEX="" CONTROL="N"><NAME>AMTINMULTIOF</NAME><TYPE>AMOUNT</TYPE><MAX_DECIMALS></MAX_DECIMALS><LBL>Số tiền chuyển là bội số của</LBL><MAXLENGTH></MAXLENGTH><DTYPE>NUMBER</DTYPE><MAX_VAL></MAX_VAL><MIN_VAL></MIN_VAL><SIZE></SIZE><ROWS></ROWS><COLS></COLS><RELATED_FIELD>TXTCONTCCY</RELATED_FIELD></FIELD></FLDSET></PART><PART ID="P3_2" NAME="P3_2" WIDTH="50"><FLDSET ID="FST_4" VIEW="SE" TYPE="SE" INDEX="1"><LBL>Tùy chọn miễn</LBL><BLOCK>BLK_ASIGNMNT_VALIDATIONS</BLOCK><HREQ>0</HREQ><HEIGHT></HEIGHT><WIDTH></WIDTH><FIELD INDEX="" CONTROL="N"><NAME>WAIVEFORLEND</NAME><TYPE>CHECKBOX</TYPE><CUSTOM><ON>Y</ON><OFF>N</OFF></CUSTOM><CHECKED>N</CHECKED><LBL>Cho người cho vay</LBL><MAXLENGTH>1</MAXLENGTH><DTYPE>VARCHAR2</DTYPE><SIZE></SIZE><ROWS></ROWS><COLS></COLS></FIELD><FIELD INDEX="" CONTROL="N"><NAME>WAIVEFORAFFIL</NAME><TYPE>CHECKBOX</TYPE><CUSTOM><ON>Y</ON><OFF>N</OFF></CUSTOM><CHECKED>N</CHECKED><LBL>Cho chi nhánh</LBL><MAXLENGTH>1</MAXLENGTH><DTYPE>VARCHAR2</DTYPE><SIZE></SIZE><ROWS></ROWS><COLS></COLS></FIELD><FIELD INDEX="" CONTROL="N"><NAME>WAIVEWITHAGENTCON</NAME><TYPE>CHECKBOX</TYPE><CUSTOM><ON>Y</ON><OFF>N</OFF></CUSTOM><CHECKED>N</CHECKED><LBL>Có sự đồng ý của đại lý</LBL><MAXLENGTH>1</MAXLENGTH><DTYPE>VARCHAR2</DTYPE><SIZE></SIZE><ROWS></ROWS><COLS></COLS></FIELD><FIELD INDEX="" CONTROL="N"><NAME>WAIVEWITHBORRCONS</NAME><TYPE>CHECKBOX</TYPE><CUSTOM><ON>Y</ON><OFF>N</OFF></CUSTOM><CHECKED>N</CHECKED><LBL>Có sự đồng ý của người vay</LBL><MAXLENGTH>1</MAXLENGTH><DTYPE>VARCHAR2</DTYPE><SIZE></SIZE><ROWS></ROWS><COLS></COLS></FIELD><FIELD INDEX="" CONTROL="N"><NAME>WAIVEWHENCMPLTRFR</NAME><TYPE>CHECKBOX</TYPE><CUSTOM><ON>Y</ON><OFF>N</OFF></CUSTOM><CHECKED>N</CHECKED><LBL>Trong khi hoàn thành chuyển khoản</LBL><MAXLENGTH>1</MAXLENGTH><DTYPE>VARCHAR2</DTYPE><SIZE></SIZE><ROWS></ROWS><COLS></COLS></FIELD></FLDSET></PART></SECTION><SECTION ID="SEC_4" COLLAPSE="N"><LBL></LBL><PART ID="P4-1" NAME="P4-1" WIDTH="33"><FLDSET ID="FST_5" VIEW="SE" TYPE="SE" INDEX="1"><LBL>Kiểm duyệt sự đồng ý</LBL><BLOCK>BLK_ASIGNMNT_VALIDATIONS</BLOCK><HREQ>0</HREQ><HEIGHT></HEIGHT><WIDTH></WIDTH><FIELD INDEX="" CONTROL="N"><NAME>VALIDBRRCNSNT</NAME><TYPE>CHECKBOX</TYPE><CUSTOM><ON>Y</ON><OFF>N</OFF></CUSTOM><CHECKED>N</CHECKED><LBL>Kiểm duyệt sự đồng ý của người vay</LBL><MAXLENGTH>1</MAXLENGTH><DTYPE>VARCHAR2</DTYPE><SIZE></SIZE><ROWS></ROWS><COLS></COLS></FIELD><FIELD INDEX="" CONTROL="N"><NAME>BCNSNTFOROLDINVST</NAME><TYPE>CHECKBOX</TYPE><CUSTOM><ON>Y</ON><OFF>N</OFF></CUSTOM><CHECKED>N</CHECKED><LBL>Nhà đầu tư hiện có</LBL><MAXLENGTH>1</MAXLENGTH><DTYPE>VARCHAR2</DTYPE><SIZE></SIZE><ROWS></ROWS><COLS></COLS></FIELD><FIELD INDEX="" CONTROL="N"><NAME>BCNSNTFORNEWINVEST</NAME><TYPE>CHECKBOX</TYPE><CUSTOM><ON>Y</ON><OFF>N</OFF></CUSTOM><CHECKED>N</CHECKED><LBL>Nhà đầu tư mới</LBL><MAXLENGTH>1</MAXLENGTH><DTYPE>VARCHAR2</DTYPE><SIZE></SIZE><ROWS></ROWS><COLS></COLS></FIELD><FIELD INDEX="" CONTROL="N"><NAME>BCNSNTFOROLDAFFIL</NAME><TYPE>CHECKBOX</TYPE><CUSTOM><ON>Y</ON><OFF>N</OFF></CUSTOM><CHECKED>N</CHECKED><LBL>Chi nhánh của nhà đầu tư hiện tại</LBL><MAXLENGTH>1</MAXLENGTH><DTYPE>VARCHAR2</DTYPE><SIZE></SIZE><ROWS></ROWS><COLS></COLS></FIELD><FIELD INDEX="" CONTROL="N"><NAME>BCONSENT_FOR_ALL</NAME><TYPE>CHECKBOX</TYPE><CUSTOM><ON>Y</ON><OFF>N</OFF></CUSTOM><CHECKED>N</CHECKED><LBL>Toàn bộ các gán</LBL><MAXLENGTH>1</MAXLENGTH><DTYPE>VARCHAR2</DTYPE><SIZE></SIZE><ROWS></ROWS><COLS></COLS></FIELD></FLDSET></PART><PART ID="P4-2" NAME="P4-2" WIDTH="33"><FLDSET ID="FST_6" VIEW="SE" TYPE="SE" INDEX="1"><LBL>Kiểm duyệt sự đồng ý</LBL><BLOCK>BLK_ASIGNMNT_VALIDATIONS</BLOCK><HREQ>0</HREQ><HEIGHT></HEIGHT><WIDTH></WIDTH><FIELD INDEX="" CONTROL="N"><NAME>VALIDISSUEBANKCNSNT</NAME><TYPE>CHECKBOX</TYPE><CUSTOM><ON>Y</ON><OFF>N</OFF></CUSTOM><CHECKED>N</CHECKED><LBL>Kiểm duyệt sự đồng ý của ngân hàng phát hành</LBL><MAXLENGTH>1</MAXLENGTH><DTYPE>VARCHAR2</DTYPE><SIZE></SIZE><ROWS></ROWS><COLS></COLS></FIELD><FIELD INDEX="" CONTROL="N"><NAME>IBCNSNTFOROLDINVET</NAME><TYPE>CHECKBOX</TYPE><CUSTOM><ON>Y</ON><OFF>N</OFF></CUSTOM><CHECKED>N</CHECKED><LBL>Nhà đầu tư hiện có</LBL><MAXLENGTH>1</MAXLENGTH><DTYPE>VARCHAR2</DTYPE><SIZE></SIZE><ROWS></ROWS><COLS></COLS></FIELD><FIELD INDEX="" CONTROL="N"><NAME>IBCNSNTFORNEWINVST</NAME><TYPE>CHECKBOX</TYPE><CUSTOM><ON>Y</ON><OFF>N</OFF></CUSTOM><CHECKED>N</CHECKED><LBL>Nhà đầu tư mới</LBL><MAXLENGTH>1</MAXLENGTH><DTYPE>VARCHAR2</DTYPE><SIZE></SIZE><ROWS></ROWS><COLS></COLS></FIELD><FIELD INDEX="" CONTROL="N"><NAME>IBCNSNTFOROLDAFFIL</NAME><TYPE>CHECKBOX</TYPE><CUSTOM><ON>Y</ON><OFF>N</OFF></CUSTOM><CHECKED>N</CHECKED><LBL>Chi nhánh của nhà đầu tư hiện tại</LBL><MAXLENGTH>1</MAXLENGTH><DTYPE>VARCHAR2</DTYPE><SIZE></SIZE><ROWS></ROWS><COLS></COLS></FIELD><FIELD INDEX="" CONTROL="N"><NAME>IBCNSNTFORALL</NAME><TYPE>CHECKBOX</TYPE><CUSTOM><ON>Y</ON><OFF>N</OFF></CUSTOM><CHECKED>N</CHECKED><LBL>Toàn bộ các gán</LBL><MAXLENGTH>1</MAXLENGTH><DTYPE>VARCHAR2</DTYPE><SIZE></SIZE><ROWS></ROWS><COLS></COLS></FIELD></FLDSET></PART><PART ID="P4-3" NAME="P4-3" WIDTH="33"><FLDSET ID="FST_7" VIEW="SE" TYPE="SE" INDEX="1"><LBL>Kiểm duyệt sự đồng ý</LBL><BLOCK>BLK_ASIGNMNT_VALIDATIONS</BLOCK><HREQ>0</HREQ><HEIGHT></HEIGHT><WIDTH></WIDTH><FIELD INDEX="" CONTROL="N"><NAME>VALIDATESWINBNKCNSNT</NAME><TYPE>CHECKBOX</TYPE><CUSTOM><ON>Y</ON><OFF>N</OFF></CUSTOM><CHECKED>N</CHECKED><LBL>Kiểm duyệt sự đồng ý của ngân hàng có hạn mức tạm thời</LBL><MAXLENGTH>1</MAXLENGTH><DTYPE>VARCHAR2</DTYPE><SIZE></SIZE><ROWS></ROWS><COLS></COLS></FIELD><FIELD INDEX="" CONTROL="N"><NAME>SLCNSNTFOROLDINVT</NAME><TYPE>CHECKBOX</TYPE><CUSTOM><ON>Y</ON><OFF>N</OFF></CUSTOM><CHECKED>N</CHECKED><LBL>Nhà đầu tư hiện có</LBL><MAXLENGTH>1</MAXLENGTH><DTYPE>VARCHAR2</DTYPE><SIZE></SIZE><ROWS></ROWS><COLS></COLS></FIELD><FIELD INDEX="" CONTROL="N"><NAME>SLCNSNTFORNEWINV</NAME><TYPE>CHECKBOX</TYPE><CUSTOM><ON>Y</ON><OFF>N</OFF></CUSTOM><CHECKED>N</CHECKED><LBL>Nhà đầu tư mới</LBL><MAXLENGTH>1</MAXLENGTH><DTYPE>VARCHAR2</DTYPE><SIZE></SIZE><ROWS></ROWS><COLS></COLS></FIELD><FIELD INDEX="" CONTROL="N"><NAME>SLCNSNTFOROLDAFFILI</NAME><TYPE>CHECKBOX</TYPE><CUSTOM><ON>Y</ON><OFF>N</OFF></CUSTOM><CHECKED>N</CHECKED><LBL>Chi nhánh của nhà đầu tư hiện tại</LBL><MAXLENGTH>1</MAXLENGTH><DTYPE>VARCHAR2</DTYPE><SIZE></SIZE><ROWS></ROWS><COLS></COLS></FIELD><FIELD INDEX="" CONTROL="N"><NAME>SLCNSNTFORALL</NAME><TYPE>CHECKBOX</TYPE><CUSTOM><ON>Y</ON><OFF>N</OFF></CUSTOM><CHECKED>N</CHECKED><LBL>Toàn bộ các gán</LBL><MAXLENGTH>1</MAXLENGTH><DTYPE>VARCHAR2</DTYPE><SIZE></SIZE><ROWS></ROWS><COLS></COLS></FIELD></FLDSET></PART></SECTION><SECTION ID="SEC_5" COLLAPSE="N"><LBL></LBL><PART ID="P5-1" NAME="P5-1" WIDTH="33"><FLDSET ID="FST_8" VIEW="ME" TYPE="ME" INDEX="1"><LBL></LBL><BLOCK>BLK_ISSUING_BANKS</BLOCK><HREQ>0</HREQ><HEIGHT></HEIGHT><WIDTH></WIDTH><PGSIZE>15</PGSIZE><FIELD INDEX="" CONTROL="N"><NAME>BANK</NAME><TYPE>TEXT</TYPE><LBL>Ngân hàng phát hành</LBL><MAXLENGTH>12</MAXLENGTH><DTYPE>VARCHAR2</DTYPE><SIZE></SIZE><ROWS></ROWS><COLS></COLS><LOV><NAME>LOV_ISSUING_BANKS</NAME><TYPE>L</TYPE></LOV></FIELD></FLDSET><FLDSET ID="FST_10" VIEW="ME" TYPE="ME" INDEX="2"><LBL></LBL><BLOCK>BLK_SWINGING_LENDERS</BLOCK><HREQ>0</HREQ><HEIGHT></HEIGHT><WIDTH></WIDTH><PGSIZE>15</PGSIZE><FIELD INDEX="" CONTROL="N"><NAME>BANK</NAME><TYPE>TEXT</TYPE><LBL>Người cho vay hạn mức tạm thời</LBL><MAXLENGTH>12</MAXLENGTH><DTYPE>VARCHAR2</DTYPE><SIZE></SIZE><ROWS></ROWS><COLS></COLS><LOV><NAME>LOV_SWINGING_LENDERS</NAME><TYPE>L</TYPE></LOV></FIELD></FLDSET></PART><PART ID="P5-2" NAME="P5-2" WIDTH="33"><FLDSET ID="FST_9" VIEW="ME" TYPE="ME" INDEX="1"><LBL></LBL><BLOCK>BLK_SIMUL_TRASFER_TRNCH</BLOCK><HREQ>0</HREQ><HEIGHT></HEIGHT><WIDTH></WIDTH><PGSIZE>15</PGSIZE><FIELD INDEX="" CONTROL="N"><NAME>OTHERTRANREFNO</NAME><TYPE>TEXT</TYPE><LBL>Chuyển các cam kết góp vốn đồng thời</LBL><MAXLENGTH>16</MAXLENGTH><DTYPE>VARCHAR2</DTYPE><SIZE></SIZE><ROWS></ROWS><COLS></COLS><LOV><NAME>LOV_SIMUL_TRANSFER_TRANCHE</NAME><TYPE>L</TYPE></LOV></FIELD></FLDSET><FLDSET ID="FST_11" VIEW="ME" TYPE="ME" INDEX="2"><LBL></LBL><BLOCK>BLK_TRNCH_UNDER_LENDER_STAT</BLOCK><HREQ>0</HREQ><HEIGHT></HEIGHT><WIDTH></WIDTH><PGSIZE>15</PGSIZE><FIELD INDEX="" CONTROL="N"><NAME>OTHERTRANCHREFNO</NAME><TYPE>TEXT</TYPE><LBL>Cam kết góp vốn được bảo đảm theo trạng thái người cho vay</LBL><MAXLENGTH>16</MAXLENGTH><DTYPE>VARCHAR2</DTYPE><SIZE></SIZE><ROWS></ROWS><COLS></COLS><LOV><NAME>LOV_TRNCH_UNDER_LENDER_STAT</NAME><TYPE>L</TYPE></LOV></FIELD></FLDSET></PART><PART ID="P5-3" NAME="P5-3" WIDTH="33"><FLDSET ID="FST_12" VIEW="SE" TYPE="SE" INDEX="1"><LBL></LBL><BLOCK>BLK_ASIGNMNT_VALIDATIONS</BLOCK><HREQ>0</HREQ><HEIGHT></HEIGHT><WIDTH></WIDTH><FIELD INDEX="" CONTROL="N"><NAME>ISSBANKSUBLIMIT</NAME><TYPE>TEXT</TYPE><MAX_DECIMALS>3</MAX_DECIMALS><LBL>Hạn mức phụ của ngân hàng phát hành</LBL><MAXLENGTH>22</MAXLENGTH><DTYPE>NUMBER</DTYPE><MAX_VAL></MAX_VAL><MIN_VAL></MIN_VAL><SIZE></SIZE><ROWS></ROWS><COLS></COLS></FIELD><FIELD INDEX="" CONTROL="N"><NAME>SWINSUBLIMIT</NAME><TYPE>TEXT</TYPE><MAX_DECIMALS>3</MAX_DECIMALS><LBL>Hạn mức phụ tạm thời</LBL><MAXLENGTH>22</MAXLENGTH><DTYPE>NUMBER</DTYPE><MAX_VAL></MAX_VAL><MIN_VAL></MIN_VAL><SIZE></SIZE><ROWS></ROWS><COLS></COLS></FIELD><FIELD INDEX="" CONTROL="N"><NAME>SPECIALCASES</NAME><TYPE>TEXT</TYPE><LBL>Trường hợp đặc biệt</LBL><MAXLENGTH>255</MAXLENGTH><DTYPE>VARCHAR2</DTYPE><SIZE></SIZE><ROWS></ROWS><COLS></COLS></FIELD><FIELD INDEX="" CONTROL="N"><NAME>SECTNO</NAME><TYPE>TEXT</TYPE><LBL>Số phần</LBL><MAXLENGTH>50</MAXLENGTH><DTYPE>VARCHAR2</DTYPE><SIZE></SIZE><ROWS></ROWS><COLS></COLS></FIELD></FLDSET><FLDSET ID="FST_13" VIEW="SE" TYPE="SE" INDEX="2"><LBL></LBL><BLOCK>BLK_ASIGNMNT_VALIDATIONS</BLOCK><HREQ>0</HREQ><HEIGHT></HEIGHT><WIDTH></WIDTH><FIELD INDEX="" CONTROL="N"><NAME>DEFLENDLANGPR</NAME><TYPE>SELECT</TYPE><OPTION SELECTED="-1" VALUE=""></OPTION><OPTION SELECTED="0" VALUE="Y">Có</OPTION><OPTION SELECTED="0" VALUE="N">Số</OPTION><LBL>Ngôn ngữ mặc định của người cho vay</LBL><MAXLENGTH>2</MAXLENGTH><DTYPE>VARCHAR2</DTYPE><SIZE></SIZE><ROWS></ROWS><COLS></COLS></FIELD><FIELD INDEX="" CONTROL="N"><NAME>BRRCNSNTDAYS</NAME><TYPE>TEXT</TYPE><MAX_DECIMALS></MAX_DECIMALS><LBL>Số ngày người vay đồng ý</LBL><MAXLENGTH>22</MAXLENGTH><DTYPE>NUMBER</DTYPE><MAX_VAL></MAX_VAL><MIN_VAL></MIN_VAL><SIZE></SIZE><ROWS></ROWS><COLS></COLS></FIELD><FIELD INDEX="" CONTROL="N"><NAME>TXTASIGNFEE</NAME><TYPE>AMOUNT</TYPE><LBL>Phí gán</LBL><MAXLENGTH></MAXLENGTH><READ_ONLY>-1</READ_ONLY><DTYPE>VARCHAR2</DTYPE><SIZE></SIZE><ROWS></ROWS><COLS></COLS><RELATED_FIELD>TXTCCY</RELATED_FIELD></FIELD><FIELD INDEX="" CONTROL="N"><NAME>TXTCCY</NAME><TYPE>TEXT</TYPE><LBL>Loại tiền</LBL><MAXLENGTH></MAXLENGTH><READ_ONLY>-1</READ_ONLY><DTYPE>VARCHAR2</DTYPE><SIZE></SIZE><ROWS></ROWS><COLS></COLS></FIELD><FIELD INDEX="" CONTROL="N"><NAME>REQSIMULTTXFROFDEAL</NAME><TYPE>CHECKBOX</TYPE><CUSTOM><ON>Y</ON><OFF>N</OFF></CUSTOM><CHECKED>N</CHECKED><LBL>Chuyển giao dịch đồng thời</LBL><MAXLENGTH>1</MAXLENGTH><DTYPE>VARCHAR2</DTYPE><SIZE></SIZE><ROWS></ROWS><COLS></COLS></FIELD><FIELD INDEX="" CONTROL="N"><NAME>NOTIFYBORROWER</NAME><TYPE>CHECKBOX</TYPE><CUSTOM><ON>Y</ON><OFF>N</OFF></CUSTOM><CHECKED>N</CHECKED><LBL>Thông báo cho người vay được gán</LBL><MAXLENGTH>1</MAXLENGTH><DTYPE>VARCHAR2</DTYPE><SIZE></SIZE><ROWS></ROWS><COLS></COLS></FIELD></FLDSET></PART></SECTION><SECTION ID="SEC_6" COLLAPSE="N"><LBL></LBL><PART ID="P6" NAME="P6" WIDTH="33"></PART><PART ID="P7" NAME="P7" WIDTH="33"></PART><PART ID="P8" NAME="P8" WIDTH="33"></PART></SECTION><SECTION ID="SEC_7" COLLAPSE="N"><LBL></LBL><PART ID="P7" NAME="P7" WIDTH="100"><SPRTCNT>3</SPRTCNT><FLDSET ID="FST_14" VIEW="SE" TYPE="SE" INDEX="1"><LBL></LBL><BLOCK>BLK_ASIGNMNT_VALIDATIONS</BLOCK><HREQ>0</HREQ><HEIGHT></HEIGHT><WIDTH></WIDTH><FIELD INDEX="" CONTROL="N" SPRT="1"><NAME>TRANCWITHMINTRFRAMT</NAME><TYPE>AMOUNT</TYPE><LBL>Cam kết góp vốn có số tiền giao dịch tối thiểu</LBL><MAXLENGTH>255</MAXLENGTH><DTYPE>VARCHAR2</DTYPE><SIZE></SIZE><ROWS></ROWS><COLS></COLS><RELATED_FIELD>TXTCCY</RELATED_FIELD><POPUPEDIT><TITLE>Cam kết góp vốn có số tiền giao dịch tối thiểu</TITLE><OK_IMG_SRC></OK_IMG_SRC><CANCEL_IMG_SRC></CANCEL_IMG_SRC></POPUPEDIT></FIELD><FIELD INDEX="" CONTROL="N" SPRT="2"><NAME>TRANTRADTO</NAME><TYPE>TEXT</TYPE><LBL>Cam kết góp vốn sẽ giao dịch đồng thời</LBL><MAXLENGTH>255</MAXLENGTH><DTYPE>VARCHAR2</DTYPE><SIZE></SIZE><ROWS></ROWS><COLS></COLS><POPUPEDIT><TITLE>Cam kết góp vốn sẽ giao dịch đồng thời</TITLE><OK_IMG_SRC></OK_IMG_SRC><CANCEL_IMG_SRC></CANCEL_IMG_SRC></POPUPEDIT></FIELD><FIELD INDEX="" CONTROL="N" SPRT="3"><NAME>REMARKS</NAME><TYPE>TEXT</TYPE><LBL>Chú thích</LBL><MAXLENGTH>255</MAXLENGTH><DTYPE>VARCHAR2</DTYPE><SIZE></SIZE><ROWS></ROWS><COLS></COLS></FIELD></FLDSET></PART></SECTION></TAB></BODY><FOOTER><TAB ID="TAB_FOOTER"><LBL></LBL></TAB></FOOTER></SCREEN></FORM>